gptprobe/__init__.py
gptprobe/keysinenviron.py
gptprobe/public_setenv.py
gptprobe/public_setenv_triple.py
gptprobe/askfor/__init__.py
gptprobe/askfor/clarification.py
gptprobe/askfor/clarificationfromquestionandanswer.py
gptprobe/askfor/dictfrompoorlyformattedtext.py
gptprobe/askfor/dictfromquestion.py
gptprobe/askfor/dictfromquestionanswerandclarification.py
gptprobe/askfor/dictfromquestionwithratification.py
gptprobe/askfor/dictfromquestionwithretries.py
gptprobe/askfor/dictfromtext.py
gptprobe/askfor/dicttext.py
gptprobe/askfor/flaw.py
gptprobe/askfor/flawfromquestionandanswer.py
gptprobe/askfor/ratification.py
gptprobe/askfor/ratificationfromquestionandanswer.py
gptprobe/askfor/rephrasing.py
gptprobe/askfor/rephrasingfromquestionandanswer.py
gptprobe/askfor/rephrasingfromquestionanswerandflaw.py
gptprobe/askfor/text.py
gptprobe/askfor/textfrompoorlyformatteddicttext.py
gptprobe/askfor/textfromquestion.py
gptprobe/utils/__init__.py
gptprobe/utils/customtypes.py
gptprobe/utils/enginedefaults.py
gptprobe/utils/equivalence.py
gptprobe/utils/parsedictrobustly.py
gptprobe-0.1.6.dist-info/LICENSE
gptprobe-0.1.6.dist-info/METADATA
gptprobe-0.1.6.dist-info/WHEEL
gptprobe-0.1.6.dist-info/entry_points.txt
gptprobe-0.1.6.dist-info/top_level.txt
gptprobe-0.1.6.dist-info/RECORD
