Metadata-Version: 2.1
Name: gptprobe
Version: 0.1.6
Summary: Probing chatgpt
Home-page: https://github.com/gptprobe/gptprobe
Author: gptprobe
Author-email: pcotton@intechinvestments.com
License: MIT
Classifier: License :: OSI Approved :: MIT License
Classifier: Programming Language :: Python :: 3
Classifier: Programming Language :: Python :: 3.7
Classifier: Programming Language :: Python :: 3.8
Classifier: Programming Language :: Python :: 3.9
License-File: LICENSE
Requires-Dist: numpy
Requires-Dist: pandas
Requires-Dist: getjson
Requires-Dist: openai
